sfisop/data_forwarder/forwarder/deploy_mongodbforwarder.sh
sfisop/data_forwarder/forwarder/deploy_thingspeakforwarder.sh
sfisop/data_forwarder/forwarder/dest_mqtt/dest_mqtt_client.py
sfisop/data_forwarder/forwarder/dest_mqtt/dest_mqtt_config.py
sfisop/data_forwarder/forwarder/dest_mqtt/dest_mqtt_forwarder.py
sfisop/data_forwarder/forwarder/dest_mqtt/dest_mqtt_forwarder_demo.py
sfisop/data_forwarder/forwarder/dest_mqtt/dest_mqtt_utils.py
sfisop/data_forwarder/forwarder/forwarder_config.py
sfisop/data_forwarder/forwarder/mongodb/mongodb_client.py
sfisop/data_forwarder/forwarder/mongodb/mongodb_config.py
sfisop/data_forwarder/forwarder/mongodb/mongodb_forwarder.py
sfisop/data_forwarder/forwarder/mongodb/mongodb_utils.py
sfisop/data_forwarder/forwarder/mqtt_forwarder.py
sfisop/data_forwarder/forwarder/tail_mgdb.sh
sfisop/data_forwarder/forwarder/tail_tp.sh
sfisop/data_forwarder/forwarder/thingspeak/thingspeak_client.py
sfisop/data_forwarder/forwarder/thingspeak/thingspeak_config.py
sfisop/data_forwarder/forwarder/thingspeak/thingspeak_forwarder.py
sfisop/data_forwarder/forwarder/thingspeak/thingspeak_utils.py
sfisop/datamodels/tsdatamodel/__init__.py
sfisop/datamodels/tsdatamodel/metadata.py
sfisop/datamodels/tsdatamodel/timeseriesdata.py
sfisop/datamodels/tsdatamodel/tsdata_utils.py
sfisop/messaging_sdk/.git/HEAD
sfisop/messaging_sdk/.git/config
sfisop/messaging_sdk/.git/description
sfisop/messaging_sdk/.git/hooks/applypatch-msg.sample
sfisop/messaging_sdk/.git/hooks/commit-msg.sample
sfisop/messaging_sdk/.git/hooks/fsmonitor-watchman.sample
sfisop/messaging_sdk/.git/hooks/post-update.sample
sfisop/messaging_sdk/.git/hooks/pre-applypatch.sample
sfisop/messaging_sdk/.git/hooks/pre-commit.sample
sfisop/messaging_sdk/.git/hooks/pre-merge-commit.sample
sfisop/messaging_sdk/.git/hooks/pre-push.sample
sfisop/messaging_sdk/.git/hooks/pre-rebase.sample
sfisop/messaging_sdk/.git/hooks/pre-receive.sample
sfisop/messaging_sdk/.git/hooks/prepare-commit-msg.sample
sfisop-0.3.5.dist-info/METADATA
sfisop-0.3.5.dist-info/WHEEL
sfisop-0.3.5.dist-info/RECORD
