Metadata-Version: 2.1
Name: sfisop
Version: 0.3.5
Summary: 
Author: Yo581515
Author-email: 581515@stud.hvl.no
Requires-Python: >=3.9,<4.0.0
Classifier: Programming Language :: Python :: 3
Classifier: Programming Language :: Python :: 3.9
Classifier: Programming Language :: Python :: 3.10
Classifier: Programming Language :: Python :: 3.11
Classifier: Programming Language :: Python :: 3.12
Requires-Dist: PyYAML (>=6.0.1,<7.0.0)
Requires-Dist: annotated-types (>=0.6.0,<1.0.0)
Requires-Dist: certifi (>=2024.2.2,<2025.0.0)
Requires-Dist: charset-normalizer (>=3.3.2,<4.0.0)
Requires-Dist: dnspython (>=2.6.1,<3.0.0)
Requires-Dist: idna (>=3.6,<4.0.0)
Requires-Dist: packaging (>=24.1,<25.0)
Requires-Dist: paho-mqtt (>=2.0.0,<3.0.0)
Requires-Dist: pydantic (>=1.10.9,<2.0.0)
Requires-Dist: pydantic_core (>=2.16.3,<3.0.0)
Requires-Dist: pymongo (>=4.6.2,<5.0.0)
Requires-Dist: pytest (>=8.3.2,<9.0.0)
Requires-Dist: python-dateutil (>=2.9.0.post0,<3.0.0)
Requires-Dist: python-decouple (>=3.8,<4.0.0)
Requires-Dist: requests (>=2.31.0,<3.0.0)
Requires-Dist: six (>=1.16.0,<2.0.0)
Requires-Dist: toml (>=0.10.2,<0.11.0)
Requires-Dist: typing_extensions (>=4.6.3,<5.0.0)
Requires-Dist: urllib3 (>=2.2.1,<3.0.0)
